setup.py
generic_crud/__init__.py
generic_crud/constants.py
generic_crud/data_types.py
generic_crud/exceptions.py
generic_crud/generic_manager.py
generic_crud/generic_service.py
generic_crud/generic_store.py
generic_crud/generic_validation.py
generic_crud/utils.py
generic_crud.egg-info/PKG-INFO
generic_crud.egg-info/SOURCES.txt
generic_crud.egg-info/dependency_links.txt
generic_crud.egg-info/pbr.json
generic_crud.egg-info/requires.txt
generic_crud.egg-info/top_level.txt