Metadata-Version: 1.0
Name: generic-crud
Version: 1.0.1
Summary: It create crud tcp apis
Home-page: UNKNOWN
Author: Om Jangir
Author-email: omjangir2006@gmail.com
License: UNKNOWN
Platform: UNKNOWN
